{"guide_design-pattern_2.md":"c0975444","guide_vue3_vite.md":"3f025cba","guide_js2file.md":"7a0d21ac","javascript_promise.md":"b0857bfc","javascript_git.md":"3aab1907","index.md":"7e55e7ea","guide_index.md":"118751d1","javascript_advance.md":"e34f62c0","life_index.md":"58eba886","javascript_h5.md":"cd129a84","javascript_index.md":"355d7522","rollup_index.md":"0e00f469","javascript_mockjs拦截原理.md":"4e1127fc","rust_questinos.md":"c9f0147d","vueanalysis_index.md":"f8b287e5","vuenextanalysis_index.md":"6bf2f329","guide_reduce.md":"91ba01d9","guide_design-pattern.md":"3833254e"}
